cloudpub/__init__.py
cloudpub/common.py
cloudpub/error.py
cloudpub/utils.py
cloudpub/aws/__init__.py
cloudpub/aws/service.py
cloudpub/aws/utils.py
cloudpub/models/__init__.py
cloudpub/models/aws.py
cloudpub/models/common.py
cloudpub/models/ms_azure.py
cloudpub/ms_azure/__init__.py
cloudpub/ms_azure/service.py
cloudpub/ms_azure/session.py
cloudpub/ms_azure/utils.py
cloudpub-1.6.0.dist-info/LICENSE
cloudpub-1.6.0.dist-info/METADATA
cloudpub-1.6.0.dist-info/WHEEL
cloudpub-1.6.0.dist-info/top_level.txt
cloudpub-1.6.0.dist-info/RECORD
