Metadata-Version: 2.1
Name: cloudpub
Version: 1.6.0
Summary: Services for publishing products in cloud environments
Home-page: https://github.com/release-engineering/cloudpub
Author: Jonathan Gangi
Author-email: jgangi@redhat.com
License: GPLv3+
Keywords: stratosphere cloudpub cloudpublish
Classifier: License :: OSI Approved :: GNU General Public License v3 or later (GPLv3+)
Classifier: Programming Language :: Python :: 3.10
Classifier: Programming Language :: Python :: 3.11
Classifier: Programming Language :: Python :: 3.12
Classifier: Programming Language :: Python :: 3.13
License-File: LICENSE
Requires-Dist: attrs
Requires-Dist: deepdiff
Requires-Dist: requests
Requires-Dist: tenacity
Requires-Dist: packaging
Requires-Dist: boto3>=1.34.117
